cheminftools/__init__.py
cheminftools/utils.py
cheminftools/data/__init__.py
cheminftools/data/config.py
cheminftools/data/data_gather.py
cheminftools/data/dataset.py
cheminftools/tools/__init__.py
cheminftools/tools/featurizer.py
cheminftools/tools/filtering.py
cheminftools/tools/sanitizer.py
cheminftools-0.1.4.dist-info/METADATA
cheminftools-0.1.4.dist-info/WHEEL
cheminftools-0.1.4.dist-info/top_level.txt
cheminftools-0.1.4.dist-info/RECORD
