Metadata-Version: 2.1
Name: cheminftools
Version: 0.1.4
Summary: A collection of tools for daily cheminformatics tasks.
Home-page: https://github.com/marcossantanaioc/cheminftools
Author: marcossantanaioc
Author-email: marcosvssantana@gmail.com
License: Apache Software License 2.0
Keywords: cheminformatics computational chemistry rdkit
Classifier: Development Status :: 4 - Beta
Classifier: Intended Audience :: Developers
Classifier: Natural Language :: English
Classifier: Programming Language :: Python :: 3.9
Classifier: Programming Language :: Python :: 3.10
Classifier: License :: OSI Approved :: Apache Software License
Requires-Python: >=3.9
Requires-Dist: psycopg2 (==2.9.6)
Requires-Dist: pytest (==7.3.1)
Requires-Dist: flake8 (==3.8.4)
Requires-Dist: fastcore (==1.5.29)
Requires-Dist: pandas (==2.0.1)
Requires-Dist: numpy (==1.24.3)
Requires-Dist: scipy (==1.10.1)
Requires-Dist: scikit-learn (==1.2.2)
Requires-Dist: rdkit-pypi (==2022.9.5)
Requires-Dist: tqdm (==4.65.0)
Requires-Dist: matplotlib (==3.7.1)
Provides-Extra: dev
